nipistaa/__init__.py
nipistaa/hook.py
nipistaa/py.typed
nipistaa/templates/__init__.py
nipistaa/templates/_commands.py
nipistaa/utils/__init__.py
nipistaa/utils/guild_command.py
nipistaa/utils/types.py
nipistaa-0.1.0.dist-info/LICENSE
nipistaa-0.1.0.dist-info/METADATA
nipistaa-0.1.0.dist-info/WHEEL
nipistaa-0.1.0.dist-info/top_level.txt
nipistaa-0.1.0.dist-info/RECORD
