Metadata-Version: 2.1
Name: nipistaa
Version: 0.1.0
Summary: The all in one lib to bootstrap your pincer bot
Home-page: UNKNOWN
Author: Sigmanificient
Author-email: contact@yohannboniface.dev
License: MIT
Project-URL: Github repository, https://github.com/Sigmanificient/nipistaa
Project-URL: Discord, https://discord.gg/8WkYz3fNFm
Project-URL: Pincer, https://github.com/pincer-org/pincer
Keywords: pincer,discord,api,asynchronous,websockets,aiohttp
Platform: unix
Platform: linux
Platform: osx
Platform: cygwin
Platform: windows
Classifier: Development Status :: 2 - Pre-Alpha
Classifier: Intended Audience :: Developers
Classifier: License :: OSI Approved :: MIT License
Classifier: Programming Language :: Python :: 3 :: Only
Classifier: Programming Language :: Python :: 3.8
Classifier: Programming Language :: Python :: 3.9
Classifier: Programming Language :: Python :: 3.10
License-File: LICENSE
Requires-Dist: pincer (>=0.15.3)
Provides-Extra: testing
Requires-Dist: mypy ; extra == 'testing'
Requires-Dist: pytest ; extra == 'testing'
